resman_client/__init__.py
resman_client/cli.py
resman_client/client.py
resman_client/ffmpeg_util.py
resman_client-1.10.dist-info/LICENSE
resman_client-1.10.dist-info/METADATA
resman_client-1.10.dist-info/WHEEL
resman_client-1.10.dist-info/entry_points.txt
resman_client-1.10.dist-info/top_level.txt
resman_client-1.10.dist-info/RECORD
