Metadata-Version: 2.1
Name: resman-client
Version: 1.10
Summary: Python client of Resman
Home-page: https://github.com/TsingJyujing/DataSpider
Author: Tsing Jyujing
Author-email: nigel434@gmail.com
Classifier: Programming Language :: Python :: 3
Classifier: License :: OSI Approved :: GNU General Public License v3 (GPLv3)
Classifier: Operating System :: OS Independent
Requires-Python: >=3.7
License-File: LICENSE
Requires-Dist: requests
Requires-Dist: python-magic
Requires-Dist: pydantic
Requires-Dist: requests-toolbelt
Requires-Dist: click
Requires-Dist: chardet
